farmware_tools/VERSION
farmware_tools/__init__.py
farmware_tools/_util.py
farmware_tools/app.py
farmware_tools/auxiliary.py
farmware_tools/device.py
farmware_tools/env.py
farmware_tools-3.5.6.dist-info/LICENSE
farmware_tools-3.5.6.dist-info/METADATA
farmware_tools-3.5.6.dist-info/WHEEL
farmware_tools-3.5.6.dist-info/top_level.txt
farmware_tools-3.5.6.dist-info/RECORD
