Metadata-Version: 2.1
Name: farmware-tools
Version: 3.5.6
Summary: Farmware convenience functions for use in FarmBot OS.
Home-page: https://github.com/FarmBot-Labs/farmware-tools
Author: FarmBot Inc.
Author-email: farmware.tools@farm.bot
License: MIT
Project-URL: FarmBot, https://farm.bot/
Keywords: farmbot,python
Platform: UNKNOWN
Classifier: Development Status :: 3 - Alpha
Classifier: License :: OSI Approved :: MIT License
Classifier: Programming Language :: Python
Classifier: Programming Language :: Python :: 2
Classifier: Programming Language :: Python :: 2.7
Classifier: Programming Language :: Python :: 3
Classifier: Programming Language :: Python :: 3.7
